{"Modules":[{"Source":"./modules/network/vcn","Key":"1.create_vcn;./modules/network/vcn","Version":"","Dir":".terraform\\modules\\7cecc149dd22b14176a0756b205361df","Root":""},{"Source":"./modules/network/subnets","Key":"1.bastion_subnet;./modules/network/subnets","Version":"","Dir":".terraform\\modules\\4e425cd5cb2027afefc0b274b6c35c8b","Root":""},{"Source":"./modules/network/subnets","Key":"1.lb_subnet;./modules/network/subnets","Version":"","Dir":".terraform\\modules\\bbdf196851a65f76bac9e23d509d80ce","Root":""},{"Source":"./modules/network/subnets","Key":"1.app_subnet;./modules/network/subnets","Version":"","Dir":".terraform\\modules\\6072db6d1573a0136f181bfd0a2ede8b","Root":""},{"Source":"./modules/network/subnets","Key":"1.db_subnet;./modules/network/subnets","Version":"","Dir":".terraform\\modules\\2f6332b3dcf1bd837eb143c50e347cf5","Root":""},{"Source":"./modules/bastion","Key":"1.create_bastion;./modules/bastion","Version":"","Dir":".terraform\\modules\\eab71a7c23a5694050bfbf27d90c50de","Root":""},{"Source":"./modules/compute","Key":"1.create_app;./modules/compute","Version":"","Dir":".terraform\\modules\\99e1855895df97bf84e963c9bf3cc4d5","Root":""},{"Source":"./modules/dbsystem","Key":"1.create_db;./modules/dbsystem","Version":"","Dir":".terraform\\modules\\18dd8493753bee03d10dfdbd39e23409","Root":""},{"Source":"./modules/loadbalancer","Key":"1.create_lb;./modules/loadbalancer","Version":"","Dir":".terraform\\modules\\d3a641450c830e7b660614b439643b78","Root":""}]}